resiliens/__init__.py
resiliens/circuit_breaker/CircuitBreaker.py
resiliens/circuit_breaker/CircuitBreakerException.py
resiliens/circuit_breaker/CircuitBreakerState.py
resiliens/circuit_breaker/CircuitBreakerStatus.py
resiliens/circuit_breaker/SlidingWindow.py
resiliens/circuit_breaker/__init__.py
resiliens/circuit_breaker/manager/CircuitBreakerManager.py
resiliens/circuit_breaker/manager/__init__.py
resiliens/fallback/Fallback.py
resiliens/fallback/__init__.py
resiliens/retryable/Retryable.py
resiliens/retryable/__init__.py
ResiliensPy-0.0.12.dist-info/METADATA
ResiliensPy-0.0.12.dist-info/WHEEL
ResiliensPy-0.0.12.dist-info/top_level.txt
ResiliensPy-0.0.12.dist-info/RECORD
